{"title":"다음 영화 ─ 박스오피스 ─ 주간","url":"https://movie.daum.net/ranking/boxoffice/weekly","favicon":"https://movie.daum.net/ranking/boxoffice/favicon.ico","elements":[{"title":"더 마블스","contents":"<span class=\"screen_out\">관객수</span>446,883명","link":"https://movie.daum.net/moviedb/main?movieId=144068","retrieved":1699838137603,"image":"https://img1.daumcdn.net/thumb/C408x596/?fname=https%3A%2F%2Ft1.daumcdn.net%2Fmovie%2Fd96483ca32e53dc6811e2c50d275fedd2d441bc3"},{"title":"그대들은 어떻게 살 것인가","contents":"<span class=\"screen_out\">관객수</span>1,729,536명","link":"https://movie.daum.net/moviedb/main?movieId=171140","retrieved":1698628387919,"image":"https://img1.daumcdn.net/thumb/C408x596/?fname=https%3A%2F%2Ft1.daumcdn.net%2Fmovie%2F814364da4037f74217243eeee6b4648d7dc2fc79"},{"title":"소년들","contents":"<span class=\"screen_out\">관객수</span>385,202명","link":"https://movie.daum.net/moviedb/main?movieId=142054","retrieved":1698628387942,"image":"https://img1.daumcdn.net/thumb/C408x596/?fname=https%3A%2F%2Ft1.daumcdn.net%2Fmovie%2Fe48f9ed4b76de90583360711e39725b67dd3049c"},{"title":"30일","contents":"<span class=\"screen_out\">관객수</span>2,082,516명","link":"https://movie.daum.net/moviedb/main?movieId=165591","retrieved":1696806985630,"image":"https://img1.daumcdn.net/thumb/C408x596/?fname=https%3A%2F%2Ft1.daumcdn.net%2Fmovie%2F8a87a8c7a462e24cb77b63b10d1497966f7c6210"},{"title":"뉴 노멀","contents":"<span class=\"screen_out\">관객수</span>61,955명","link":"https://movie.daum.net/moviedb/main?movieId=161233","retrieved":1699838137618,"image":"https://img1.daumcdn.net/thumb/C408x596/?fname=https%3A%2F%2Ft1.daumcdn.net%2Fmovie%2Fb1c637d374c7f62cde230dcaa8121822f76a3c75"},{"title":"톡 투 미","contents":"<span class=\"screen_out\">관객수</span>143,996명","link":"https://movie.daum.net/moviedb/main?movieId=166851","retrieved":1699233319368,"image":"https://img1.daumcdn.net/thumb/C408x596/?fname=https%3A%2F%2Ft1.daumcdn.net%2Fmovie%2Fb51274ce05d5b9a3072f4c88fd6ad3b03d89e941"},{"title":"용감한 시민","contents":"<span class=\"screen_out\">관객수</span>261,932명","link":"https://movie.daum.net/moviedb/main?movieId=159263","retrieved":1698628387928,"image":"https://img1.daumcdn.net/thumb/C408x596/?fname=https%3A%2F%2Ft1.daumcdn.net%2Fmovie%2F8a41fde7f5dda3d369818fa80baf3b2472c789b7"},{"title":"블루 자이언트","contents":"<span class=\"screen_out\">관객수</span>100,736명","link":"https://movie.daum.net/moviedb/main?movieId=167998","retrieved":1698023550553,"image":"https://img1.daumcdn.net/thumb/C408x596/?fname=https%3A%2F%2Ft1.daumcdn.net%2Fmovie%2F0965d6d350f199711ffcc30e590f99fc6181dab8"},{"title":"1947 보스톤","contents":"<span class=\"screen_out\">관객수</span>1,010,904명","link":"https://movie.daum.net/moviedb/main?movieId=123211","retrieved":1696202166864,"image":"https://img1.daumcdn.net/thumb/C408x596/?fname=https%3A%2F%2Ft1.daumcdn.net%2Fmovie%2Fa77f64489aceb34ee1a29dc29822d76ca3902a91"},{"title":"플라워 킬링 문","contents":"<span class=\"screen_out\">관객수</span>161,754명","link":"https://movie.daum.net/moviedb/main?movieId=150473","retrieved":1698023550530,"image":"https://img1.daumcdn.net/thumb/C408x596/?fname=https%3A%2F%2Ft1.daumcdn.net%2Fmovie%2F54d73561dce387c9a482cee6a47beacb6318d18e"},{"title":"마이 샤이니 월드","contents":"<span class=\"screen_out\">관객수</span>19,056명","link":"https://movie.daum.net/moviedb/main?movieId=174119","retrieved":1699233319389,"image":"https://img1.daumcdn.net/thumb/C408x596/?fname=https%3A%2F%2Ft1.daumcdn.net%2Fmovie%2F4196e4cdc819ef9c288b040035a366cb0729fbad"},{"title":"만추 리마스터링","contents":"<span class=\"screen_out\">관객수</span>858,261명","link":"https://movie.daum.net/moviedb/main?movieId=51326","retrieved":1699838137630,"image":"https://img1.daumcdn.net/thumb/C408x596/?fname=https%3A%2F%2Ft1.daumcdn.net%2Fmovie%2F7859f072a0aab0a15f5ea5b1572d16ec4114c42e"},{"title":"퍼피 구조대: 더 마이티 무비","contents":"<span class=\"screen_out\">관객수</span>166,362명","link":"https://movie.daum.net/moviedb/main?movieId=171625","retrieved":1696806985645,"image":"https://img1.daumcdn.net/thumb/C408x596/?fname=https%3A%2F%2Ft1.daumcdn.net%2Fmovie%2F78c39629c6e80eee5fead6c3d8d12e124a15e32d"},{"title":"테일러 스위프트 디 에라스 투어","contents":"<span class=\"screen_out\">관객수</span>20,451명","link":"https://movie.daum.net/moviedb/main?movieId=174406","retrieved":1699233319375,"image":"https://img1.daumcdn.net/thumb/C408x596/?fname=https%3A%2F%2Ft1.daumcdn.net%2Fmovie%2Fa92b521216c7cf6d9d714d798d47bfbb46e5d806"},{"title":"괴인","contents":"<span class=\"screen_out\">관객수</span>8,329명","link":"https://movie.daum.net/moviedb/main?movieId=164398","retrieved":1699838137639,"image":"https://img1.daumcdn.net/thumb/C408x596/?fname=https%3A%2F%2Ft1.daumcdn.net%2Fmovie%2Fbed3c28cdc72f6c3cd138174cfab160450652cc6"}]}