{"title":"다음영화 뉴스 ─ 최신","url":"https://movie.daum.net/contents/news?type=recent","favicon":"https://movie.daum.net/contents/favicon.ico","elements":[{"title":"[리뷰-영화 '티탄']감각적 영상미, 파격적 이야기 속에 사랑과 구원의 의미 묻다","contents":"[서울경제] 시작과 함께 골절 부위에 철심을 박는 모습을 연상케 하듯 티타늄으로 뇌를 고정하는 수술 장면이 관객을 맞는다. 그 뒤로 인간과 무생물, 남성과 여성, 삶과 죽음 혹은 생명의 탄생과 살인 같은 언뜻 양립하기 어려워 보이는 것들이 불과 물, 기름 등 강렬한 이미지에 실려 함께 등장한다. 중반까지 어디로 튈지 모르는 스토리의 흐름은 신선한 자극을","link":"https://v.daum.net/v/20211205080045925","retrieved":1638576000000,"image":"https://img1.daumcdn.net/thumb/S384x240/?fname=https%3A%2F%2Ft1.daumcdn.net%2Fnews%2F202112%2F05%2Fseouleconomy%2F20211205080047815sgih.png"},{"title":"\"환상의 듀엣\"..마가렛 퀄리X시고니 위버 '마이 뉴욕 다이어리'[MK무비]","contents":"“특별해지고 싶어요.” 12월 극장가가 한 층 풍성해진다. 오는 9일, 작가를 꿈꾸는 ‘조안나’(마가렛 퀄리)가 뉴욕 최고의 작가 에이전시에 입사해서 겪는 파란만장한 이야기를 다룬 영화 ‘마이 뉴욕 다이어리’가 개봉한다. 필리프 팔라도 감독이 메가폰을 잡았고, 시고니 위버·마가렛 퀄리가 주연을 맡았다. 영화는 전통을 고집하는 작가 에이전시 CEO ‘마가렛","link":"https://v.daum.net/v/20211205075101843","retrieved":1638576000000,"image":"https://img1.daumcdn.net/thumb/S384x240/?fname=https%3A%2F%2Ft1.daumcdn.net%2Fnews%2F202112%2F05%2Fstartoday%2F20211205075104736depi.jpg"},{"title":"전종서, 데뷔도 열애도 솔직, 파격 [N초점]","contents":"(서울=뉴스1) 정유진 기자 = 파격적이다. 영화 '버닝'(감독 이창동)으로 데뷔한 전종서를 설명할 때 종종 쓰이던 이 표현은 그가 보여준 또 한 번의 행보를 이야기 할 때도 잘 어울린다. 올해 27세, 데뷔 4년차인 배우 전종서는 현재 당당하게 열애 중이며, 이 사실을 굳이 감추지도 않았다. 전종서의 소속사 마이컴퍼니는 최근 뉴스1에 \"이충현 감독과","link":"https://v.daum.net/v/20211205073001738","retrieved":1638576000000,"image":"https://img1.daumcdn.net/thumb/S384x240/?fname=https%3A%2F%2Ft1.daumcdn.net%2Fnews%2F202112%2F05%2FNEWS1%2F20211205073002093xpjm.jpg"},{"title":"'죽지않는 인간들의 밤' 신정원 감독 사망, 향년 47세","contents":"[뉴스엔 허민녕 기자] ‘시실리 2㎞’ ‘죽지않는 인간들의 밤’을 연출한 감독 신정원이 47세란 안타까운 나이에 세상을 떠났다. 사인은 급성 패혈증. 관계자에 따르면, 신정원 감독은 12월3일 고열을 동반한 호흡 곤란 증세로 응급실을 찾았으며, 이후 중환자실로 옮겨졌으나 12월4일 숨을 거두고 말았다. 그는 간경화를 앓고 있었던 것으로 알려지고 있다.","link":"https://v.daum.net/v/20211205060005138","retrieved":1638576000000,"image":"https://img1.daumcdn.net/thumb/S384x240/?fname=https%3A%2F%2Ft1.daumcdn.net%2Fnews%2F202112%2F05%2Fnewsen%2F20211205060005662skim.jpg"},{"title":"\"토비 맥과이어 사진 투척\", 톰 홀랜드 이번에도 스포일러?[해외이슈]","contents":"[마이데일리 = 곽명동 기자]'스파이더맨: 노 웨이 홈' 공개를 앞둔 배우 톰 홀랜드(25)가 샘 레이미 감독의 ‘스파이더맨’에 출연했던 토비 맥과이어(46) 사진을 올려 궁금증이 커지고 있다. 톰 홀랜드는 최근 미국에서 시작된 영화 '스파이더맨: 노 웨이 홈' 티켓 예매에 맞춰 SNS에 토비 맥과이어 사진을 올렸다. 2002년 5월 개봉한 이 영화에","link":"https://v.daum.net/v/20211205060003133","retrieved":1638576000000,"image":"https://img1.daumcdn.net/thumb/S384x240/?fname=https%3A%2F%2Ft1.daumcdn.net%2Fnews%2F202112%2F05%2Fmydaily%2F20211205060003767iztg.jpg"}]}