{"title":"다음영화 뉴스 ─ 최신","url":"https://movie.daum.net/contents/news?type=recent","favicon":"https://movie.daum.net/contents/favicon.ico","elements":[{"title":"'콘크리트 유토피아' 박서준이 사생활 공개에 민감해진 이유 [인터뷰 맛보기]","contents":"[티브이데일리 김종은 기자] 배우 박서준이 사생활 공개에 민감해진 이유를 들려줬다. 박서준은 1일 오후 서울 삼청동 소재의 한 카페에서 진행된 영화 '콘크리트 유토피아'(감독 엄태화·제작 클라이맥스 스튜디오) 개봉 기념 인터뷰에서 \"사생활 공개에 민감해진 특별한 계기가 있다\"라고 말했다. 최근 유튜버 수스(xooos)와 열애설에 휘말린 바 있는 박서준은","link":"https://v.daum.net/v/20230801161318245","retrieved":1690848000000,"image":"https://img1.daumcdn.net/thumb/S384x240/?fname=https%3A%2F%2Ft1.daumcdn.net%2Fnews%2F202308%2F01%2Ftvdaily%2F20230801161319281szwm.jpg"},{"title":"'더 문' 설경구 \"♥송윤아 반응? 웅장하다고 했다\" [인터뷰③]","contents":"[OSEN=하수정 기자] 설경구가 영화 '더 문'을 접한 아내 송윤아의 반응을 공개했다. 1일 오후 서울 종로구에 위치한 카페에서는 영화 '더 문'의 주연 배우 설경구의 인터뷰가 진행됐다. &nbsp; '더 문'(감독 김용화, 제공배급 CJ ENM, 제작 CJ ENM STUDIOS 블라드스튜디오, 감독 김용화)은 사고로 인해 홀로 달에 고립된 우주 대원 선우와","link":"https://v.daum.net/v/20230801161020141","retrieved":1690848000000,"image":"https://img1.daumcdn.net/thumb/S384x240/?fname=https%3A%2F%2Ft1.daumcdn.net%2Fnews%2F202308%2F01%2Fpoctan%2F20230801161022530feud.jpg"},{"title":"주지훈 \"톰 크루즈와 비교 감사…영혼 갈아넣었다\" [인터뷰 종합]","contents":"(엑스포츠뉴스 김유진 기자) 배우 주지훈이 '비공식작전'에 쏟아 부었던 열정과 애정을 고백하며 작품을 향한 관심과 따뜻한 시선을 함께 당부했다. 주지훈은 1일 오전 서울 종로구 삼청동의 한 카페에서 열린 영화 '비공식작전'(감독 김성훈) 인터뷰에서 다양한 이야기를 전했다. '비공식작전'은 실종된 동료를 구하기 위해 레바논으로 떠난 외교관 민준(하정우 분)과","link":"https://v.daum.net/v/20230801155009369","retrieved":1690848000000,"image":"https://img1.daumcdn.net/thumb/S384x240/?fname=https%3A%2F%2Ft1.daumcdn.net%2Fnews%2F202308%2F01%2Fxportsnews%2F20230801155010461rsjp.jpg"},{"title":"홀로 살아남은 아파트 한 동...천국일까 지옥일까","contents":"요즘의 우리는 철근 부족으로 무너진 아파트 주차장이나 빗물이 가득 들어찬 지하 차도를 보며 재난의 원인을 찾고, 인재(人災) 여부를 확인하느라 바쁘다. 그러나 어떤 재난은 설명되지도, 설명할 필요를 느끼지도 못하게 다가온다. 엄태화 감독의 영화 ‘콘트리트 유토피아’ 속에서의 재난이 바로 그렇다. 이유를 알 수 없는 대지진이 서울을 덮치는 충격적인 장면이 스","link":"https://v.daum.net/v/20230801154503200","retrieved":1690848000000,"image":"https://img1.daumcdn.net/thumb/S384x240/?fname=https%3A%2F%2Ft1.daumcdn.net%2Fnews%2F202308%2F01%2Fmk%2F20230801154507876uqbt.jpg"},{"title":"우리는 왜 김기영의 '하녀'를 보는가","contents":"[김규종 기자] ▲ &nbsp;영화 &lt;하녀&gt;(1960) 스틸 이미지ⓒ 김기영 프로덕션&nbsp; 김기영 감독(1919~1998)은 살아생전에 경험하지 못한 유명세를 고인이 된 후에 누린 특이한 이력의 소유자다. 1960년 개봉 영화 &lt;하녀&gt;가 서울에서만 10만 관객을 동원하여 성공을 거둔다. 그 이전에 연출한 영화는 1955년 데뷔작 &lt;주검의 상자&gt;를 비롯해 모두 7편이지만","link":"https://v.daum.net/v/20230801154201071","retrieved":1690848000000,"image":"https://img1.daumcdn.net/thumb/S384x240/?fname=https%3A%2F%2Ft1.daumcdn.net%2Fnews%2F202308%2F01%2Fohmynews%2F20230801154203681ygbt.jpg"},{"title":"'콘크리트 유토피아' 이병헌 놀란 CG급 연기력…\"'오징어 게임2' 재밌다\"(종합)[Oh!쎈 인터뷰]","contents":"[OSEN=김보라 기자]&nbsp;“장르에 맞춰서 연기하는 배우들이 많지는 않다.” 이병헌은 1일 오후 서울 소격동의 한 카페에서 진행된 OSEN과의 인터뷰에서 “배우들은 자신의 역할을 보여줄 수 있는 캐릭터를 연기하고, 나머지는 감독들이 만들어내는 거다. 그런 점에서 이 영화가 완성도 높다는 생각이 들었다. 여러 가지 장르색이 보였다는 점에서 기분이 좋다”라며","link":"https://v.daum.net/v/20230801153922981","retrieved":1690848000000,"image":"https://img1.daumcdn.net/thumb/S384x240/?fname=https%3A%2F%2Ft1.daumcdn.net%2Fnews%2F202308%2F01%2Fpoctan%2F20230801153922282xzcy.jpg"},{"title":"기대와 달라서 좋은 ‘콘크리트 유토피아’ [쿡리뷰]","contents":"대지진이 일어난 서울 한복판에 아파트 한 채만 덩그러니 남는다면 그곳은 낙원일까 지옥일까. 대다수의 황궁아파트 주민들에게 그곳은 낙원이다. 이들은 말한다. “아파트 밖으로 나가면 다 죽는다”고. “아파트는 주민의 것”을 외치며 외부인을 내쫓는 이들의 앞날은 어떻게 될까? 기발한 상상에서 출발한 영화 ‘콘크리트 유토피아’(감독 엄태화)는 현실과 면밀하게","link":"https://v.daum.net/v/20230801153603814","retrieved":1690848000000,"image":"https://img1.daumcdn.net/thumb/S384x240/?fname=https%3A%2F%2Ft1.daumcdn.net%2Fnews%2F202308%2F01%2Fkukinews%2F20230801153605905dbyk.jpg"},{"title":"'바비', 이미 약 1조 벌어...박스오피스 새 역사 쓴다 [할리웃통신]","contents":"[TV리포트=유비취 기자] 영화 '바비'의 흥행 가도가 심상치 않다. 지난 30일(현지 시간) 연예 매체 버라이어티는 영화 '바비'가 박스오피스 기록을 세웠다고 보도했다. '바비'는 북미에서 지난 29일, 30일 주말 양일간 9300만 달러(한화 약 1,191억 원)의 수익을 올렸다. 이는 전주인 개봉 주말 이후 단 43%만 감소한 수치로 역대 영화 역사","link":"https://v.daum.net/v/20230801153101640","retrieved":1690848000000,"image":"https://img1.daumcdn.net/thumb/S384x240/?fname=https%3A%2F%2Ft1.daumcdn.net%2Fnews%2F202308%2F01%2Ftvreport%2F20230801153107339bbyz.jpg"},{"title":"[인터뷰②] ‘콘크리트’ 이병헌 “엄태화 감독, 박보영에게 날 ‘갈치’라 생각하라고…”","contents":"배우 이병헌이 영화 ‘콘크리트 유토피아’ 촬영장에서의 비하인드를 공개했다. 이병헌은 1일 오전 영화 ‘콘크리트 유토피아’ 개봉을 앞두고 서울 종로구의 한 카페에서 진행된 인터뷰에서 박보영과 연기합에 대해 “회사가 같은데 많이 볼 일이 없었다. ‘과속스캔들’ 이미지가 컸는데 이번 영화에서 새로운 면을 봤다”고 이야기했다. ‘콘크리트 유토피아’에는 이병헌과","link":"https://v.daum.net/v/20230801152544432","retrieved":1690848000000,"image":"https://img1.daumcdn.net/thumb/S384x240/?fname=https%3A%2F%2Ft1.daumcdn.net%2Fnews%2F202308%2F01%2Filgansports%2F20230801152545589ixsj.jpg"},{"title":"이병헌 \"'오겜2' 추측, 맞는 것 하나도 없어…황동혁은 천재\"[인터뷰]①","contents":"[이데일리 스타in 김보영 기자] ‘콘크리트 유토피아’ 이병헌이 차기작인 넷플릭스 ‘오징어 게임2’의 스토리를 둘러싼 각종 추측들에 직접 답하며 작품에 임하게 된 소감과 과정을 털어놨다. 이병헌은 영화 ‘콘크리트 유토피아’(감독 엄태화)의 개봉을 앞둔 1일 오후 서울 종로구의 한 카페에서 취재진과 인터뷰를 진행했다. 앞서 이병헌은 넷플릭스 ‘오징어 게임","link":"https://v.daum.net/v/20230801151550994","retrieved":1690848000000,"image":"https://img1.daumcdn.net/thumb/S384x240/?fname=https%3A%2F%2Ft1.daumcdn.net%2Fnews%2F202308%2F01%2FEdaily%2F20230801151553550nqtj.jpg"},{"title":"'더 문' 설경구 \"이준호, 잘 될 줄 알았다\" [인터뷰②]","contents":"[TV리포트=김연주 기자] 배우 설경구가 '더 문'에서 연기 호흡을 맞춘 도경수를 극찬했다.&nbsp; 1일 오후 서울 종로구 삼청동 소재 한 카페에서 영화 '더 문'으로 관객을 만나는 주연 배우 설경구와의 인터뷰가 진행됐다.&nbsp; '더 문'은 사고로 인해 홀로 달에 고립된 우주 대원 선우와 필사적으로 그를 구하려는 전 우주센터장 재국의 사투를 그린 영화다.&nbsp; 극중 설","link":"https://v.daum.net/v/20230801151030762","retrieved":1690848000000,"image":"https://img1.daumcdn.net/thumb/S384x240/?fname=https%3A%2F%2Ft1.daumcdn.net%2Fnews%2F202308%2F01%2Ftvreport%2F20230801151037450dvqt.jpg"},{"title":"'더 문' 설경구, \"김용화 감독 즉각적인 디렉팅…오히려 고마운 부분\"[인터뷰③]","contents":"[텐아시아=이하늘 기자]영화 '더 문'의 배우 설경구는 호흡을 맞춘 김용화 감독이 아이 같은 부분이 있으며, 오히려 연기하는 데 편했다고 설명했다. 설경구는 1일 서울&nbsp;안국동의 한 카페에서 영화 ‘더 문’(감독 김용화) 관련 인터뷰에 나섰다. '더 문'은 사고로 인해 홀로 달에 고립된 우주 대원 선우(도경수)와 필사적으로 그를 구하려는 전 우주센터장","link":"https://v.daum.net/v/20230801150517572","retrieved":1690848000000,"image":"https://img1.daumcdn.net/thumb/S384x240/?fname=https%3A%2F%2Ft1.daumcdn.net%2Fnews%2F202308%2F01%2F10asia%2F20230801150520259zumg.jpg"},{"title":"'더 문' 설경구, \"연기돌 이준호·임시완→도경수와 만남…오히려 내가 운 좋다\"[인터뷰②]","contents":"[텐아시아=이하늘 기자]영화 ‘더 문’의 배우 설경구는 도경수 배우 이전에 연기돌들과 인연이 많은데, 호흡을 맞췄던 배우 모두 잘 된 것 같다며 자신은 운이 좋다고 너스레를 떨었다. 설경구는 1일 서울&nbsp;안국동의 한 카페에서 영화 ‘더 문’(감독 김용화) 관련 인터뷰에 나섰다. '더 문'은 사고로 인해 홀로 달에 고립된 우주 대원 선우(도경수)와 필사","link":"https://v.daum.net/v/20230801150511567","retrieved":1690848000000,"image":"https://img1.daumcdn.net/thumb/S384x240/?fname=https%3A%2F%2Ft1.daumcdn.net%2Fnews%2F202308%2F01%2F10asia%2F20230801150514557ckjl.jpg"},{"title":"'더 문' 설경구, \"한국형 SF가 지닌 선입견 깰 것…기술력 놀라워\"[인터뷰①]","contents":"[텐아시아=이하늘 기자]배우 설경구는 영화 ‘더 문’이 한국형 SF가 가진 선입견을 깬 것 같다며 호불호가 있더라도 박수를 쳐줄 만한 영화라고 설명했다. 설경구는 1일 서울&nbsp;안국동의 한 카페에서 영화 ‘더 문’(감독 김용화) 관련 인터뷰에 나섰다. '더 문'은 사고로 인해 홀로 달에 고립된 우주 대원 선우(도경수)와 필사적으로 그를 구하려는 전 우주","link":"https://v.daum.net/v/20230801150502560","retrieved":1690848000000,"image":"https://img1.daumcdn.net/thumb/S384x240/?fname=https%3A%2F%2Ft1.daumcdn.net%2Fnews%2F202308%2F01%2F10asia%2F20230801150506747yiaa.jpg"},{"title":"'더 문' 설경구 \"사실 SF 즐기지 않아...'더 문'으로 선입견 깼다\" [인터뷰①]","contents":"[TV리포트=김연주 기자] 배우 설경구가 한국형 SF 영화 '더 문'으로 관객을 만난다.&nbsp; 1일 오후 서울 종로구 삼청동 소재 한 카페에서 영화 '더 문'의 개봉을 앞두고 주연 배우 설경구와 인터뷰가 진행됐다.&nbsp; '더 문'은 사고로 인해 홀로 달에 고립된 우주 대원 선우와 필사적으로 그를 구하려는 전 우주센터장 재국의 사투를 그린 영화다.&nbsp; 극중 설경구는","link":"https://v.daum.net/v/20230801150130409","retrieved":1690848000000,"image":"https://img1.daumcdn.net/thumb/S384x240/?fname=https%3A%2F%2Ft1.daumcdn.net%2Fnews%2F202308%2F01%2Ftvreport%2F20230801150136335molm.jpg"},{"title":"[인터뷰③] 이병헌 \"박서준X박보영, 예쁘고 잘생긴 줄만 알았는데…\" ('콘크리트 유토피아')","contents":"[스포츠조선 안소윤 기자] '콘크리트 유토피아' 이병헌이 후배 박서준과 박보영을 극찬했다. 이병헌은 1일 서울 종로구 삼청동 한 카페에서 스포츠조선과 만나 \"박보영과 박서준은 정말 선남선녀인 친구들이다\"라고 했다. '콘크리트 유토피아'는 이병헌과 박서준, 박보영의 만남으로 올여름 최고의 기대작으로 주목을 받았다. 이병헌은 극 중 민성을 연","link":"https://v.daum.net/v/20230801145526149","retrieved":1690848000000,"image":"https://img1.daumcdn.net/thumb/S384x240/?fname=https%3A%2F%2Ft1.daumcdn.net%2Fnews%2F202308%2F01%2FSpoChosun%2F20230801145527365rygq.jpg"},{"title":"'더 문' 설경구 \"도경수, 맑은 눈 뒤 뭐가 숨겨져 있는지 궁금해\" [인터뷰②]","contents":"[마이데일리 = 양유진 기자] 배우 설경구가 그룹 엑소 멤버 겸 배우 도경수와의 연기 합을 돌이켰다. 1일 서울 종로구 안국동 한 카페에서 영화 '더 문'으로 돌아온 설경구와 만났다. '더 문'은 2029년, 사고로 홀로 달에 고립된 우주 대원 선우(도경수)와 필사적으로 그를 구하려는 전 우주센터장 재국(설경구)의 사투를 그린 우주 생존 드라마다. 천","link":"https://v.daum.net/v/20230801145241033","retrieved":1690848000000,"image":"https://img1.daumcdn.net/thumb/S384x240/?fname=https%3A%2F%2Ft1.daumcdn.net%2Fnews%2F202308%2F01%2Fmydaily%2F20230801145241595stft.jpg"},{"title":"설경구 \"'더 문', 제작비 280억 원…가성비 좋은 체험형 영화\" [인터뷰①]","contents":"[마이데일리 = 양유진 기자] 배우 설경구가 '더 문'을 \"가성비 좋은 체험형 영화\"라 칭했다. 1일 서울 종로구 안국동 한 카페에서 영화 '더 문'으로 돌아온 설경구와 만났다. '더 문'은 2029년, 사고로 홀로 달에 고립된 우주 대원 선우(도경수)와 필사적으로 그를 구하려는 전 우주센터장 재국(설경구)의 사투를 그린 우주 생존 드라마다. 천만 관","link":"https://v.daum.net/v/20230801145235029","retrieved":1690848000000,"image":"https://img1.daumcdn.net/thumb/S384x240/?fname=https%3A%2F%2Ft1.daumcdn.net%2Fnews%2F202308%2F01%2Fmydaily%2F20230801145235392dnuc.jpg"},{"title":"“꺼지지 않는 엠버의 불꽃” 엘리멘탈, 월요일에도 10만명 동원 “600만 예약”[MD픽]","contents":"[마이데일리 = 곽명동 기자]역주행 신화 ‘엘리멘탈’이 개봉 7주차 평일에도 10만 관객을 동원하며 뜨겁게 질주하고 있다. 8월 1일 영진위 통합전산망에 따르면, ‘엘리멘탈’은 7월 31일 월요일 하루동안 10만 6,770명의 관객을 불러모아 박스오피스 2위에 올랐다. 누적관객수는 577만 9,492명이다. 통상 월요일은 주말 다음날이어서 관객이 떨어","link":"https://v.daum.net/v/20230801144830886","retrieved":1690848000000,"image":"https://img1.daumcdn.net/thumb/S384x240/?fname=https%3A%2F%2Ft1.daumcdn.net%2Fnews%2F202308%2F01%2Fmydaily%2F20230801144830318lino.jpg"},{"title":"“그놈 잘될 줄 알았다” 설경구, 이준호·임시완·도경수 연기돌 콜렉터(종합)[EN:인터뷰]","contents":"[뉴스엔 배효주 기자] 유독 '연기돌'들과 좋은 호흡을 보여준 설경구. 그가 \"도경수에게 '날 만나는 애들 다 잘 됐다' 했다\"며 '더 문'의 흥행에도 자신감을 드러냈다. 영화 '더 문'(감독 김용화)에 출연한 설경구는 8월 1일 서울 종로구 모처에서 진행된 인터뷰를 통해 출연 계기 등을 밝혔다. 오는 2일 개봉하는 '더 문'은 사고로 인해 홀로 달에 고","link":"https://v.daum.net/v/20230801144036537","retrieved":1690848000000,"image":"https://img1.daumcdn.net/thumb/S384x240/?fname=https%3A%2F%2Ft1.daumcdn.net%2Fnews%2F202308%2F01%2Fnewsen%2F20230801144038023ivie.jpg"}]}