{"title":"다음영화 뉴스 ─ 최신","url":"https://movie.daum.net/contents/news?type=recent","favicon":"https://movie.daum.net/contents/favicon.ico","elements":[{"title":"‘케이티♥’ 송중기 “팔불출 같은데”…아들 사진 ‘깜짝’ 공개 (인터뷰)","contents":"배우 송중기가 아내 케이티 루이스 사운더스에 대한 이야기를 솔직하게 전했다. 25일 오후 서울시 종로구 소격동 한 카페에서 송중기는 영화 ‘화란’(감독 김창훈) 관한 인터뷰를 진행했다. 송중기는 지난 1월 영국 출신 배우 케이티 루이스 사운더스와 혼인신고를 하고 6월 득남했다. 좋은 소식이 전해지기 전에 두 사람은 각종 루머로 힘든 나날을 보냈다. 그는 “","link":"https://v.daum.net/v/20230925180301186","retrieved":1695600000000,"image":"https://img1.daumcdn.net/thumb/S384x240/?fname=https%3A%2F%2Ft1.daumcdn.net%2Fnews%2F202309%2F25%2Fmksports%2F20230925180302584hxvp.jpg"},{"title":"456만달러 상금, 역대 리얼리티 중 최고 ‘오징어게임:더 챌린지’ 11월22일 공개","contents":"[뉴스엔 배효주 기자] '오징어 게임'이 456만 달러의 상금을 걸고 리얼 서바이벌 게임 '오징어 게임: 더 챌린지'로 돌아온다. 넷플릭스 '오징어 게임: 더 챌린지'가 11월 22일 공개된다. 전 세계에서 모인 456명의 참가자가 456만 달러의 상금을 차지하는 최후의 승자가 되기 위해 극악무도한 게임에 도전하는 서바이벌 예능이다. 공개된 티저 예고편은","link":"https://v.daum.net/v/20230925175808006","retrieved":1695600000000,"image":"https://img1.daumcdn.net/thumb/S384x240/?fname=https%3A%2F%2Ft1.daumcdn.net%2Fnews%2F202309%2F25%2Fnewsen%2F20230925175808164wkoa.jpg"},{"title":"[인터뷰] ‘30일’ 강하늘 “결혼 로망? 집에 가만히 있는 거 좋아했으면…”","contents":"배우 강하늘이 자신의 결혼 로망을 이야기했다. 25일 서울 종로구 한 카페에서 영화 ‘30일’ 주역 강하늘의 인터뷰가 진행됐다. ‘30일’은 서로의 지질함과 똘기를 견디다 못해 마침내 완벽하게 남남이 되기 직전 동반기억상실증에 걸려버린 정열(강하늘)과 나라(정소민)의 이야기를 담은 코미디 영화. 강하늘은 나라의 남편이자 변호사 정열 역을 맡았다. 이날","link":"https://v.daum.net/v/20230925175308784","retrieved":1695600000000,"image":"https://img1.daumcdn.net/thumb/S384x240/?fname=https%3A%2F%2Ft1.daumcdn.net%2Fnews%2F202309%2F25%2Filgansports%2F20230925175310146bjcd.jpg"},{"title":"\"운명적 상대 아직 못 만나\"…'30일' 강하늘 밝힌 #결혼 #오징어게임2(종합) [인터뷰]","contents":"[OSEN=김보라 기자]&nbsp;‘30일’ 노정열(강하늘 분)은 공부는 잘하지만 자격지심이 깊은 찌질한 남자다. 변호사 준비생 시절, 금수저로 자란 홍나라(정소민 분)와 결혼해 행복이 시작되는 줄 알았으나 두 사람은 연애 시절 보지 못했던 서로의 단점을 지적하며 결국 이혼에 이르게 된다. ‘30일’은 그동안 봐왔던 로맨스 코미디처럼 예상이 가면서도 의외의 곳에","link":"https://v.daum.net/v/20230925175024667","retrieved":1695600000000,"image":"https://img1.daumcdn.net/thumb/S384x240/?fname=https%3A%2F%2Ft1.daumcdn.net%2Fnews%2F202309%2F25%2Fpoctan%2F20230925175024883akwz.jpg"},{"title":"\"대체할 수 없는\"…'발레리나' 김지훈, 전종서 극찬에 플러팅 '오해' (엑's 현장)[종합]","contents":"(엑스포츠뉴스 황수연 기자) 김지훈이 상대역인 전종서의 연기를 극찬했다. 25일 서울 마포구 호텔 나루 서울 엠갤러리에서 넷플릭스 영화 '발레리나' 제작보고회가 진행됐다. 이 자리에는 전종서, 김지훈, 박유림, 이충현 감독이 참석했다.&nbsp; '발레리나'는 경호원 출신 옥주(전종서 분)가 소중한 친구 민희(박유림)를 죽음으로 몰아간 최프로(김지훈)을 쫓으며 펼치","link":"https://v.daum.net/v/20230925175003654","retrieved":1695600000000,"image":"https://img1.daumcdn.net/thumb/S384x240/?fname=https%3A%2F%2Ft1.daumcdn.net%2Fnews%2F202309%2F25%2Fxportsnews%2F20230925175004775aoji.jpg"},{"title":"'발레리나' 전종서♥이충현 감독, 눈빛만 봐도 아는 시너지…\"재미있게 찍어\"","contents":"(왼쪽부터) 전종서, 이충현 감독. (사진=뉴스1)[이데일리 스타in 김보영 기자] 배우 전종서가 넷플릭스 영화 ‘콜’ 이후 영화 ‘발레리나’로 연인인 이충현 감독과 다시 한 번 작업한 소감과 계기를 밝혔다. 25일 서울 마포구 마포동 호텔 나루 서울 엠겔러리에서 열린 넷플릭스 영화 ‘발레리나’(감독 이충현) 제작보고회에는 이충현 감독과 배우 전종서,","link":"https://v.daum.net/v/20230925174902623","retrieved":1695600000000,"image":"https://img1.daumcdn.net/thumb/S384x240/?fname=https%3A%2F%2Ft1.daumcdn.net%2Fnews%2F202309%2F25%2FEdaily%2F20230925175230582bxsp.jpg"},{"title":"'30일' 남대중 감독 \"강하늘·정소민 코믹 연기, 미안할 정도로 만족\" [엑's 인터뷰]","contents":"(엑스포츠뉴스 김유진 기자) 남대중 감독이 '30일'을 함께 한 강하늘과 정소민을 칭찬했다. 남대중 감독은 25일 오후 서울 종로구 팔판동의 한 카페에서 열린 영화 '30일'인터뷰에서 다양한 이야기를 전했다. '30일'은 드디어 D-30, 서로의 지질함과 똘기를 견디다 못해 마침내 완벽하게 남남이 되기 직전 동반기억상실증에 걸려버린 정열(강하늘 분)과 나라","link":"https://v.daum.net/v/20230925174002308","retrieved":1695600000000,"image":"https://img1.daumcdn.net/thumb/S384x240/?fname=https%3A%2F%2Ft1.daumcdn.net%2Fnews%2F202309%2F25%2Fxportsnews%2F20230925174003932mero.jpg"},{"title":"활동 10개월 남은 케플러에게도 ‘마법 같은 순간’ 올까 [D:현장]","contents":"그룹 케플러(Kep1er)가 지난 4월 발매한 ‘러브스트럭!’ 이후 5개월 만에 컴백했다. 그 사이 데뷔 후 첫 일본 아레나 투어를 성공적으로 마무리했다. 짧은 시간이지만 그 안에서 이룬 성장을 이번 신보 ‘매직 아워’(Magic Hour)를 통해 보여주겠다는 각오다. 케플러는 25일 오후 서울 광진구 광장동 예스24라이브홀에서 쇼케이스를 열고 “앨범을","link":"https://v.daum.net/v/20230925173631161","retrieved":1695600000000,"image":"https://img1.daumcdn.net/thumb/S384x240/?fname=https%3A%2F%2Ft1.daumcdn.net%2Fnews%2F202309%2F25%2Fdailian%2F20230925173632306sqxe.jpg"},{"title":"\"두유 노 킴스비디오?\"…타란티노 단골 가게의 영화 같은 부활","contents":"\"  두유 노 킴스비디오(Do you know Kim’s video)?  \"   뉴욕 이스트 빌리지에서 시작된 이 질문은, 이탈리아 살레미까지 이어진다. 영화 '킴스비디오'의 한 장면이다. 킴스비디오는 뉴욕에 있던 비디오 대여점이다. 1986년 개업해 5만 5000편의 방대한 컬렉션을 갖고 25만 명의 회원에게 영화를 빌려줬다. 11개 체인점에 300명","link":"https://v.daum.net/v/20230925171900525","retrieved":1695600000000,"image":"https://img1.daumcdn.net/thumb/S384x240/?fname=https%3A%2F%2Ft1.daumcdn.net%2Fnews%2F202309%2F25%2Fjoongang%2F20230925171901444ftgt.jpg"},{"title":"학폭, 종말, 사이비종교까지 어디로 튈지 모를 이야기들","contents":"[김형욱 기자] ▲ &nbsp;영화 &lt;지옥만세&gt; 포스터.ⓒ 찬란&nbsp; 어느 공터, 교복을 입은 가해자 학생들이 생일을 축하한다며 주저앉아 있는 단발머리 황선우의 얼굴에&nbsp;케이크를&nbsp;묻힌다. 한편 송나미는 엄마의 가게 방에서 노래를 들으며 춤을 추다가 엄마한테 혼나고 집을 나간다. 그녀는 자살 시도를 했는데 이번이 처음은 아닌 것 같다. 둘은 친구들이 모두 수학여행을 갔을","link":"https://v.daum.net/v/20230925171502373","retrieved":1695600000000,"image":"https://img1.daumcdn.net/thumb/S384x240/?fname=https%3A%2F%2Ft1.daumcdn.net%2Fnews%2F202309%2F25%2Fohmynews%2F20230925171504393yozk.jpg"},{"title":"‘녹야’ 판빙빙X이주영, BIFF 참석[공식]","contents":"제73회 베를린국제영화제 파노라마 섹션 공식 초청작이자 판빙빙, 이주영의 첫 호흡으로 기대를 모으는 영화 ‘녹야’가 제28회 부산국제영화제(BIFF) ‘갈라 프레젠테이션’ 섹션에 공식 초청됐다. 영화 ‘녹야’는 낯선 곳에서 쳇바퀴 같은 삶을 사는 ‘진샤’(판빙빙)가 자유로운 영혼의 ‘초록머리 여자’(이주영)를 만나 돌이킬 수 없는 밤으로 뛰어드는 이야기를","link":"https://v.daum.net/v/20230925170612047","retrieved":1695600000000,"image":"https://img1.daumcdn.net/thumb/S384x240/?fname=https%3A%2F%2Ft1.daumcdn.net%2Fnews%2F202309%2F25%2Fstartoday%2F20230925170613413xclk.jpg"},{"title":"'연인' 이충현 감독·전종서, 발레리나'로 감성 누아르 새 장 연다 [D:현장]","contents":"영화계 대표 커플 이충현 감독과 배우 전종서가 '콜'에 이어 액션 영화 '발레리나'로 다시 손 잡았다. 25일 오후 서울 마포구 마포동 호텔 나루 서울 엠갤러리에서는 이충현 감독, 배우 전종서, 김지훈, 박유림이 참석한 가운데 넷플릭스 영화 '발레리나' 제작보고회가 진행됐다. '발레리나'는 경호원 출신 옥주(전종서 분)가 소중한 친구 민희(박유림 분)를","link":"https://v.daum.net/v/20230925170447984","retrieved":1695600000000,"image":"https://img1.daumcdn.net/thumb/S384x240/?fname=https%3A%2F%2Ft1.daumcdn.net%2Fnews%2F202309%2F25%2Fdailian%2F20230925170449389rpwn.jpg"},{"title":"강하늘 \"'오겜' 출연 감사할 따름..지친 것이 원동력 될 때도\" [인터뷰②]","contents":"[스타뉴스 | 김나연 기자] 강하늘 / 사진=티에이치컴퍼니배우 강하늘이 '오징어 게임' 시즌2 출연에 대해 조심스럽게 언급했다. 25일 서울시 종로구 소격동의 한 카페에서 영화 '30일'의 배우 강하늘과 만나 다양한 이야기를 나눴다. '30일'은 드디어 D-30, 서로의 찌질함과 똘기를 견디다 못해 마침내 완벽하게 남남이 되기 직전 동반기억상실증에","link":"https://v.daum.net/v/20230925165500475","retrieved":1695600000000,"image":"https://img1.daumcdn.net/thumb/S384x240/?fname=https%3A%2F%2Ft1.daumcdn.net%2Fnews%2F202309%2F25%2Fstarnews%2F20230925165502061rovr.jpg"},{"title":"'8년째 굳건' 홍상수‧김민희, 13번째 협업…'우리의 하루' 10월 개봉[공식]","contents":"[스포티비뉴스=김현록 기자]홍상수 감독 신작 '우리의 하루'가 오는 10월 19일 개봉을 확정했다. 홍상수 감독의 30번쨰 장편영화 '우리의 하루'(in our day)가 제76회 칸국제영화제 감독주간 폐막작으로 월드 프리미어 상영 후 10월 19일 국내 개봉을 준비하며 국내 포스터와 예고편을 공개했다. 홍상수 감독이 각본 감독 촬영 편집 음악을 모","link":"https://v.daum.net/v/20230925165339407","retrieved":1695600000000,"image":"https://img1.daumcdn.net/thumb/S384x240/?fname=https%3A%2F%2Ft1.daumcdn.net%2Fnews%2F202309%2F25%2Fspotvnews%2F20230925165341763gfos.jpg"},{"title":"“미숙했고, 실언했다” 아빠 된 송중기, 아내 케이티 루머·경력단절 논란 심경(종합)[EN:인터뷰]","contents":"[뉴스엔 배효주 기자] 논란들에 \"내가 미숙했다\"고 말한 송중기. 한 아이의 아빠가 된 그는 \"더 좋은 사람이 되고 싶다\"며 자신을 둘러싼 이슈들에 솔직히 답했다. 영화 '화란'(감독 김창훈)에 출연한 송중기는 9월 25일 서울 종로구 모처에서 진행된 인터뷰를 통해 작품에 대한 애정부터 새롭게 꾸린 가정에 대한 책임감 등을 전했다. 오는 10월 11일","link":"https://v.daum.net/v/20230925163458614","retrieved":1695600000000,"image":"https://img1.daumcdn.net/thumb/S384x240/?fname=https%3A%2F%2Ft1.daumcdn.net%2Fnews%2F202309%2F25%2Fnewsen%2F20230925163458453tlhr.jpg"},{"title":"[인터뷰④]'무빙' 류승룡 \"치킨집 설정은 원작서부터, 차기작도 닭 관한 작품\"","contents":"[스포츠조선 정빛 기자] 배우 류승룡이 디즈니+ '무빙' 역할 중 치킨집 사장이라는 설정을 언급했다. 류승룡은 25일 서울 종로 삼청동 한 카페에서 스포츠조선과 만나 \"치킨집 사장 설정은 원작에서부터 나온 것\"이라며 \"차기작도 닭에 관한 작품\"이라고 했다. '무빙'은 초능력을 숨긴 채 현재를 살아가는 아이들과 아픈 비밀을 감춘 채 과거를","link":"https://v.daum.net/v/20230925163454608","retrieved":1695600000000,"image":"https://img1.daumcdn.net/thumb/S384x240/?fname=https%3A%2F%2Ft1.daumcdn.net%2Fnews%2F202309%2F25%2FSpoChosun%2F20230925163455023syfb.jpg"},{"title":"송중기 \"경력 단절, 불편한 이슈인지 몰랐다…그래서 영어공부 하고 있다\"('화란')[인터뷰③]","contents":"[OSEN=김보라 기자]&nbsp;(인터뷰②에 이어) 배우 송중기(38)가 칸영화제에서 ‘losing my job’이라는 표현을 썼던 것과 관련, “그래서 제가 영어공부를 하고 있다”고 정중하지만 유쾌하게 해명했다. 송중기는 25일 오후 서울 소격동의 한 카페에서 진행된 OSEN과의 인터뷰에서 칸영화제를 찾은 중국 시나연예와 가졌던 인터뷰 답변에 관련된 질문을","link":"https://v.daum.net/v/20230925163022396","retrieved":1695600000000,"image":"https://img1.daumcdn.net/thumb/S384x240/?fname=https%3A%2F%2Ft1.daumcdn.net%2Fnews%2F202309%2F25%2Fpoctan%2F20230925163022791lzdn.jpg"},{"title":"'화란' 송중기 \"경력단절 발언 불편해할 줄 몰라, 신중하지 못했다\" [인터뷰 맛보기]","contents":"[티브이데일리 최하나 기자] ‘화란’의 배우 송중기가 경력단절 발언에 대해 이야기했다. 송중기는 25일 오후 서울시 종로구 삼청동 카페에서 진행된 영화 ‘화란’(감독 김창훈) 인터뷰에서 경력단절 발언에 대해 언급했다. 앞서 송중기는 중국 매체 시나연예와의 인터뷰에서 “때로는 연예계에서 누군가의 남편, 아빠가 된다는 것은 일자리를 잃는다는 것을 의미한다”","link":"https://v.daum.net/v/20230925160607282","retrieved":1695600000000,"image":"https://img1.daumcdn.net/thumb/S384x240/?fname=https%3A%2F%2Ft1.daumcdn.net%2Fnews%2F202309%2F25%2Ftvdaily%2F20230925160608576efdd.jpg"},{"title":"추석 마무리는 코미디지‥‘30일’ 흥행 계보 잇는다","contents":"[뉴스엔 배효주 기자] '30일'이 추석 코미디 영화의 흥행 계보를 잇는다. 10월 3일 개봉하는 영화 '30일'(감독 남대중)은 드디어 D-30, 서로의 찌질함과 똘기를 견디다 못해 마침내 완벽하게 남남이 되기 직전 동반기억상실증에 걸려버린 '정열'(강하늘)과 '나라'(정소민)의 코미디. ‘동반기억상실’이라는 단어 자체만으로도 신선하고 흥미로운 소재로","link":"https://v.daum.net/v/20230925160044051","retrieved":1695600000000,"image":"https://img1.daumcdn.net/thumb/S384x240/?fname=https%3A%2F%2Ft1.daumcdn.net%2Fnews%2F202309%2F25%2Fnewsen%2F20230925160045282fjnx.jpg"},{"title":"'화란' 송중기 \"아내 케이티 아직 영화 못봐, 육아하니 여유 無\" [인터뷰 맛보기]","contents":"[티브이데일리 최하나 기자] ‘화란’의 배우 송중기가 아내 케이티 루이스 사운더스에 대해 이야기했다. 송중기는 25일 오후 서울시 종로구 삼청동 카페에서 진행된 영화 ‘화란’(감독 김창훈) 인터뷰에서 칸국제영화제 초청 소감을 전했다. 앞서 송중기는 지난 5월 영화 ‘화란’으로 칸국제영화제 주목할만한 시선에 공식초청, 생애 첫 칸 레드카펫을 밟은 바 있다","link":"https://v.daum.net/v/20230925160008014","retrieved":1695600000000,"image":"https://img1.daumcdn.net/thumb/S384x240/?fname=https%3A%2F%2Ft1.daumcdn.net%2Fnews%2F202309%2F25%2Ftvdaily%2F20230925160009308uaya.jpg"}]}