{"title":"다음영화 뉴스 ─ 최신","url":"https://movie.daum.net/contents/news?type=recent","favicon":"https://movie.daum.net/contents/favicon.ico","elements":[{"title":"김하늘→여진구·유지태→조이현..22년만 돌아온 '동감' (엑's 현장)[종합]","contents":"(엑스포츠뉴스 김예은 기자) 여진구와 조이현이 리메이크작 '동감'으로 돌아온다. 17일 오전 서울 용산구 CGV용산아이파크몰에서 영화 '동감'(감독 서은영) 제작보고회가 진행됐다. 이날 배우 여진구, 조이현, 김혜윤, 나인우, 배인혁과 서은영 감독이 참석했다.&nbsp; '동감'은 1999년의 용(여진구 분)과 2022년의 무늬(조이현)가 우연히 오래된 무전기를 통","link":"https://v.daum.net/v/20221017161049520","retrieved":1665964800000,"image":"https://img1.daumcdn.net/thumb/S384x240/?fname=https%3A%2F%2Ft1.daumcdn.net%2Fnews%2F202210%2F17%2Fxportsnews%2F20221017161050840fzay.jpg"},{"title":"'브로맨스 전문' 이성민 \"덩치 큰 남주혁, 아기 같은 임시완과 다른 느낌\"('리멤버')[인터뷰②]","contents":"[텐아시아=강민경 기자] 배우 이성민이 영화 '리멤버'에서 호흡을 맞춘 남주혁에 대해 언급했다. 이성민은 17일 오후 서울 종로구 삼청동 한 카페에서 영화 '리멤버'(감독 이일형) 라운드 인터뷰를 진행했다. '리멤버'는 가족을 모두 죽게 만든 친일파를 찾아 60년간 계획한 복수를 감행하는 알츠하이머 환자 필주(이성민 역)와 의도치 않게 그의 복수에 휘","link":"https://v.daum.net/v/20221017160055041","retrieved":1665964800000,"image":"https://img1.daumcdn.net/thumb/S384x240/?fname=https%3A%2F%2Ft1.daumcdn.net%2Fnews%2F202210%2F17%2F10asia%2F20221017160058314tvbr.jpg"},{"title":"'아이폰' 쓰는 이성민 \"카카오 서비스 장애, 난 불편하지 않았는데..\"('리멤버')[인터뷰①]","contents":"[텐아시아=강민경 기자] 배우 이성민이 최근 일어난 카카오 서비스 장애에 대해 언급했다. 이성민은 17일 오후 서울 종로구 삼청동 한 카페에서 영화 '리멤버'(감독 이일형) 라운드 인터뷰를 진행했다. '리멤버'는 가족을 모두 죽게 만든 친일파를 찾아 60년간 계획한 복수를 감행하는 알츠하이머 환자 필주(이성민 역)와 의도치 않게 그의 복수에 휘말리게","link":"https://v.daum.net/v/20221017160048034","retrieved":1665964800000,"image":"https://img1.daumcdn.net/thumb/S384x240/?fname=https%3A%2F%2Ft1.daumcdn.net%2Fnews%2F202210%2F17%2F10asia%2F20221017160053799foen.jpg"},{"title":"'동감' 배인혁 \"엄마, 아빠의 사진첩 보며 90년대 의상 공부했다\"","contents":"영화 '동감'의 제작보고회가 17일(월) 오전 11시 CGV 용산아이파크몰에서 진행되었다. 이날 행사에는 서은영 감독, 여진구, 조이현, 김혜윤, 나인우, 배인혁이 참석해 영화에 대해 이야기했다. 배인혁은 \"'은성'을 연기했다.\"라고 캐릭터를 소개하며 \"시대적인 감성을 표현할수 있을거 같아서 이 작품을 선택했다.\"라며 작품에 출연하게 된 이유를 밝혔다.","link":"https://v.daum.net/v/20221017153832866","retrieved":1665964800000,"image":"https://img1.daumcdn.net/thumb/S384x240/?fname=https%3A%2F%2Ft1.daumcdn.net%2Fnews%2F202210%2F17%2FiMBC%2F20221017153833933pdqc.jpg"},{"title":"'동감' 나인우 \"살면서 단 한번도 시대에 맞다는 말 들어본 적 없다\"","contents":"영화 '동감'의 제작보고회가 17일(월) 오전 11시 CGV 용산아이파크몰에서 진행되었다. 이날 행사에는 서은영 감독, 여진구, 조이현, 김혜윤, 나인우, 배인혁이 참석해 영화에 대해 이야기했다. 나인우는 \"극중에서 '영지'를 맡았다. 떨린다.\"라고 캐릭터를 소개하며 \"현대 사회가 바쁘고 여유가 부족한데 시나리오를 읽을때 잠시 그걸 잊고 빠져들게 되더","link":"https://v.daum.net/v/20221017153822859","retrieved":1665964800000,"image":"https://img1.daumcdn.net/thumb/S384x240/?fname=https%3A%2F%2Ft1.daumcdn.net%2Fnews%2F202210%2F17%2FiMBC%2F20221017153823762drna.jpg"},{"title":"'동감' 김혜윤 \"캐릭터와 비슷하게 실제로 승부욕 커, 이 악물고 펌프했다\"","contents":"영화 '동감'의 제작보고회가 17일(월) 오전 11시 CGV 용산아이파크몰에서 진행되었다. 이날 행사에는 서은영 감독, 여진구, 조이현, 김혜윤, 나인우, 배인혁이 참석해 영화에 대해 이야기했다. 김혜윤은 \"오랜만에 기자님들을 만난다. '한솔' 연기했다\"라고 캐릭터를 소개하며 \"시나리오를 처음 읽었을때 다른 시대를 살아가는 두 남녀가 소통하는 방식이 흥","link":"https://v.daum.net/v/20221017153808843","retrieved":1665964800000,"image":"https://img1.daumcdn.net/thumb/S384x240/?fname=https%3A%2F%2Ft1.daumcdn.net%2Fnews%2F202210%2F17%2FiMBC%2F20221017153810012jnnj.jpg"},{"title":"'동감' 조이현 \"저희 만의 색깔로 요즘 세대를 그려내고 싶었다\"","contents":"영화 '동감'의 제작보고회가 17일(월) 오전 11시 CGV 용산아이파크몰에서 진행되었다. 이날 행사에는 서은영 감독, 여진구, 조이현, 김혜윤, 나인우, 배인혁이 참석해 영화에 대해 이야기했다. 조이현은 \"'무늬'를 맡았다. 편안하고 따뜻한 분위기의 영화나 드라마 촬영에 고파있었는데 우연치 않게 이 작품이 그 시기에 들어와서 대본을 딱 한번 읽고 바","link":"https://v.daum.net/v/20221017153739809","retrieved":1665964800000,"image":"https://img1.daumcdn.net/thumb/S384x240/?fname=https%3A%2F%2Ft1.daumcdn.net%2Fnews%2F202210%2F17%2FiMBC%2F20221017153744540chyn.jpg"},{"title":"'동감' 여진구 \"20대 청춘의 모습을 필모에 남기고 싶어 출연 결심\"","contents":"영화 '동감'의 제작보고회가 17일(월) 오전 11시 CGV 용산아이파크몰에서 진행되었다. 이날 행사에는 서은영 감독, 여진구, 조이현, 김혜윤, 나인우, 배인혁이 참석해 영화에 대해 이야기했다. 여진구는 \"사랑을 쫓는 남자 '용'을 연기했다.\"라고 캐릭터를 설명하며 \"청춘을 다루는 영화를 만나기 드물고 20대의 청춘 작품을 필모에 남기고 싶다는 욕심이","link":"https://v.daum.net/v/20221017153717785","retrieved":1665964800000,"image":"https://img1.daumcdn.net/thumb/S384x240/?fname=https%3A%2F%2Ft1.daumcdn.net%2Fnews%2F202210%2F17%2FiMBC%2F20221017153718738jfpn.jpg"},{"title":"'동감' 서은영 \"원작영화와 주인공의 성별을 바꿔, 그래서 연출을 결심\"","contents":"영화 '동감'의 제작보고회가 17일(월) 오전 11시 CGV 용산아이파크몰에서 진행되었다. 이날 행사에는 서은영 감독, 여진구, 조이현, 김혜윤, 나인우, 배인혁이 참석해 영화에 대해 이야기했다. 서은영 감독은 \"'동감'은 99년을 사는 '용'과 2022년을 사는 '무늬'가 HAM을 사용해 교감하는 이야기\"라고 작품을 설명했다. 그러며 \"영화를 시작할때","link":"https://v.daum.net/v/20221017153624725","retrieved":1665964800000,"image":"https://img1.daumcdn.net/thumb/S384x240/?fname=https%3A%2F%2Ft1.daumcdn.net%2Fnews%2F202210%2F17%2FiMBC%2F20221017153625977ujrs.jpg"},{"title":"이성민 \"남주혁, 맑고 듬직한 친구..군대 건강히 다녀오길\" [인터뷰①]","contents":"[스타뉴스 김미화 기자] 배우 이성민이 17일 오후 서울 종로구 삼청동의 한 카페에서 진행된 영화 '리멤버' 개봉 관련 인터뷰를 위해 포즈를 취하고 있다.  이성민은 극 중 뇌종양 말기, 80대 알츠하이머 환자인 한필주 역을 맡았다.   '리멤버'는 가족을 모두 죽게 만든 친일파를 찾아 60년간 계획한 복수를 감행하는 알츠하이머 환자 필주(이성민 분)와 의","link":"https://v.daum.net/v/20221017152532138","retrieved":1665964800000,"image":"https://img1.daumcdn.net/thumb/S384x240/?fname=https%3A%2F%2Ft1.daumcdn.net%2Fnews%2F202210%2F17%2Fstarnews%2F20221017152534279hfce.jpg"},{"title":"오대환X오윤아 '미스매치' 크랭크인..코믹 가족극[공식]","contents":"[뉴스엔 배효주 기자] 오대환과 오윤아 주연 '미스매치'가 크랭크인했다. 10월 14일 크랭크인한 영화 '미스매치'(감독 손태웅)는 갑작스러운 사고를 겪은 ‘봉수’(오대환)가 깨어난 이후 기억의 오작동으로 모든 관계들이 미스매치되면서 벌어지는 대환장 코믹가족극이다. 오대환은 '미스매치'에서 갑작스러운 사고로 황당한 인생 재부팅을 당하게 되는 남자 ‘봉수","link":"https://v.daum.net/v/20221017152220006","retrieved":1665964800000,"image":"https://img1.daumcdn.net/thumb/S384x240/?fname=https%3A%2F%2Ft1.daumcdn.net%2Fnews%2F202210%2F17%2Fnewsen%2F20221017152220928rbne.jpg"},{"title":"'리멤버' 이성민 \"노인 분장만 150시간..목디스크도 생겨\"","contents":"(서울=연합뉴스) 김정진 기자 = 하얗게 센 머리, 구부정한 자세와 느린 걸음걸이, 작게 떨리는 쉰 목소리까지. 오는 26일 개봉을 앞둔 영화 '리멤버' 속 이성민은 온전한 80대의 모습이다. 1968년생인 그는 실제 나이보다 30살가량 많은 80대 노인 한필주를 연기했다. 얼굴과 손의 주름 등을 표현하기 위해 영화 촬영 내내 특수분장에만 하루 2시간 이상","link":"https://v.daum.net/v/20221017151557742","retrieved":1665964800000,"image":"https://img1.daumcdn.net/thumb/S384x240/?fname=https%3A%2F%2Ft1.daumcdn.net%2Fnews%2F202210%2F17%2Fyonhap%2F20221017151557919mpzr.jpg"},{"title":"\"브로맨스 전문\" 이성민 밝힌 임시완·남주혁·송중기 호흡(종합)[EN:인터뷰]","contents":"[뉴스엔 배효주 기자] 자타가 공인하는 '브로맨스 전문가' 이성민이 '리멤버'에서 남주혁과 색다른 호흡을 맞춘 소감을 밝혔다. 영화 '리멤버'(감독 이일형)에 출연한 이성민은 10월 17일 서울 종로구 모처에서 진행된 인터뷰를 통해 개봉을 앞둔 소회를 전했다. 오는 26일 개봉하는 '리멤버'는 가족을 모두 죽게 만든 친일파를 찾아 60년간 계획한 복수를","link":"https://v.daum.net/v/20221017151534730","retrieved":1665964800000,"image":"https://img1.daumcdn.net/thumb/S384x240/?fname=https%3A%2F%2Ft1.daumcdn.net%2Fnews%2F202210%2F17%2Fnewsen%2F20221017151534910mype.jpg"},{"title":"'헤어질 결심' 북미 개봉 후 호평, 오스카 레이스 청신호 [무비노트]","contents":"[티브이데일리 최하나 기자] 박찬욱 감독의 '헤어질 결심'이 미국 아카데미 시상식 유력 후보로 급부상하고 있다. '헤어질 결심'이 북미 개봉 후 호평을 받으면서 시상식의 전초전으로 불리는 오스카 레이스에 청신호가 켜졌다. 영화 '헤어질 결심'(감독 박찬욱·제작 모호필름)이 지난 14일 북미에서 개봉된 가운데, 주요 외신들의 극찬이 쏟아지고 있다. 뉴욕타","link":"https://v.daum.net/v/20221017150406243","retrieved":1665964800000,"image":"https://img1.daumcdn.net/thumb/S384x240/?fname=https%3A%2F%2Ft1.daumcdn.net%2Fnews%2F202210%2F17%2Ftvdaily%2F20221017150407961jooj.jpg"},{"title":"이성민 \"'입대' 남주혁, 무조건 건강히 다녀오길..임시완보다 듬직하더라\" ('리멤버') [MD인터뷰]","contents":"[마이데일리 = 김나라 기자] 배우 이성민이 '리멤버'에서 남주혁과 호흡을 맞춘 소감을 밝혔다. 이성민은 17일 오후 서울 종로구 소격동 한 카페에서 마이데일리와 인터뷰를 진행했다. 오는 26일 신작 '리멤버'(감독 이일형) 개봉을 앞두고 만나, 이와 관련 에피소드들을 들려줬다 '리멤버'는 가족을 모두 죽게 만든 친일파를 찾아 60년간 계획한 복수를 감행","link":"https://v.daum.net/v/20221017145321774","retrieved":1665964800000,"image":"https://img1.daumcdn.net/thumb/S384x240/?fname=https%3A%2F%2Ft1.daumcdn.net%2Fnews%2F202210%2F17%2Fmydaily%2F20221017145321930fwgy.jpg"},{"title":"아시아★ 참여로 빛난 부국제, 예매권 논란 '옥의 티' 남아","contents":"코로나 아픔 딛고 3년 만에 정상 개최…16만 여명 부산 찾아 성료 [더팩트ㅣ이한림 기자] 부산국제영화제가 열흘 동안 약 16만 명의 관객이 다녀간 가운데 성황리에 막을 내렸다. 신종 코로나바이러스 감염증(코로나19) 여파로 3년 만에 오프라인으로 열린 이번 영화제는 한국의 송강호, 홍콩의 양조위, 일본의 츠마부키 사토시 등 아시아를 대표하는 정상급","link":"https://v.daum.net/v/20221017143852201","retrieved":1665964800000,"image":"https://img1.daumcdn.net/thumb/S384x240/?fname=https%3A%2F%2Ft1.daumcdn.net%2Fnews%2F202210%2F17%2FTHEFACT%2F20221017143854067mwun.jpg"},{"title":"[종합] \"내 필모에 꼭!\" 여진구♥조이현, MZ 청춘의 유지태♥김하늘 로맨스 新 해석('동감')","contents":"[텐아시아=강민경 기자] 배우 여진구, 조이현, 김혜윤, 나인우, 배인혁이 영화 '동감'으로 뭉쳤다. 다섯 사람은 풋풋하고 싱그러운 청춘의 첫사랑을 이야기한다. 특히 점점 추워지는 날씨에 딱 어울리는 청춘 로맨스 한 편을 선보인다. 17일 오전 서울 용산구 CGV용산아이파크몰에서 영화 '동감'(감독 서은영) 제작보고회가 열렸다. 이 자리에는 서은영 감독","link":"https://v.daum.net/v/20221017140026402","retrieved":1665964800000,"image":"https://img1.daumcdn.net/thumb/S384x240/?fname=https%3A%2F%2Ft1.daumcdn.net%2Fnews%2F202210%2F17%2F10asia%2F20221017140030288ucrp.jpg"},{"title":"유지태·김하늘의 아련 멜로 '동감'..여진구·조이현의 풋풋한 청춘 멜로로 [종합]","contents":"[스타뉴스 CGV용산=김미화 기자] 배우 배인혁, 김혜윤, 여진구, 조이현, 나인우가 17일 오전 서울 용산 아이파크몰 CGV에서 진행된 영화 '동감' 제작보고회에 참석해 포즈를 취하고 있다.  '동감'은 1999년의 '용'(여진구 분)과 2022년의 '무늬'(조이현 분)가 우연히 오래된 무전기를 통해 소통하면서 벌어지는 이야기를 그린 청춘 로맨스다. 11","link":"https://v.daum.net/v/20221017140001374","retrieved":1665964800000,"image":"https://img1.daumcdn.net/thumb/S384x240/?fname=https%3A%2F%2Ft1.daumcdn.net%2Fnews%2F202210%2F17%2Fstarnews%2F20221017140720321xmtk.jpg"},{"title":"\"'동감' 안 할 이유 없었다\"..여진구 조이현→배인혁 청춘 로맨스[MK현장]","contents":"청춘 배우들이 풋풋하고 아련한 로맨스 ‘동감’으로 뭉쳤다. 17일 오전 서울 CGV용산 아이파크몰에서 영화 ‘동감’ 제작보고회가 열렸다. 서은영 감독과 배우 여진구 조이현 김혜윤 나인우 배인혁이 참석했다. 2000년 개봉한 동명의 작품을 리메이크한 ‘동감’은 1999년의 용과 2022년의 무늬가 우연히 오래된 무전기를 통해 소통하면서 벌어지는 이야기를","link":"https://v.daum.net/v/20221017135949367","retrieved":1665964800000,"image":"https://img1.daumcdn.net/thumb/S384x240/?fname=https%3A%2F%2Ft1.daumcdn.net%2Fnews%2F202210%2F17%2Fstartoday%2F20221017135954709chgi.jpg"},{"title":"이성민, 카카오 먹통 언급 \"난 하나도 안 불편해..어플 사용 안해서\"[EN:인터뷰③]","contents":"[뉴스엔 배효주 기자] 이성민이 \"'리멤버'는 젊은 세대와 나이 든 세대의 이야기\"라고 말하며 관람을 독려했다. 영화 '리멤버'(감독 이일형)에 출연한 이성민은 10월 17일 서울 종로구 모처에서 진행된 인터뷰를 통해 \"'리멤버' 출연을 통해 세대 간 소통에 대해 이야기 하고 싶었다\"고 말문을 열었다. 오는 26일 개봉하는 '리멤버'는 가족을 모두 죽게","link":"https://v.daum.net/v/20221017135345057","retrieved":1665964800000,"image":"https://img1.daumcdn.net/thumb/S384x240/?fname=https%3A%2F%2Ft1.daumcdn.net%2Fnews%2F202210%2F17%2Fnewsen%2F20221017135345543wsfs.jpg"}]}